MANIFEST.in
README.rst
setup.cfg
setup.py
docs/CREDITS.rst
docs/HISTORY.rst
docs/INSTALL.rst
docs/LICENSE.GPL
docs/LICENSE.txt
src/collective/__init__.py
src/collective.twitter.portlets.egg-info/PKG-INFO
src/collective.twitter.portlets.egg-info/SOURCES.txt
src/collective.twitter.portlets.egg-info/dependency_links.txt
src/collective.twitter.portlets.egg-info/entry_points.txt
src/collective.twitter.portlets.egg-info/namespace_packages.txt
src/collective.twitter.portlets.egg-info/not-zip-safe
src/collective.twitter.portlets.egg-info/requires.txt
src/collective.twitter.portlets.egg-info/top_level.txt
src/collective/twitter/__init__.py
src/collective/twitter/portlets/__init__.py
src/collective/twitter/portlets/config.py
src/collective/twitter/portlets/configure.zcml
src/collective/twitter/portlets/interfaces.py
src/collective/twitter/portlets/portlets.zcml
src/collective/twitter/portlets/setuphandlers.py
src/collective/twitter/portlets/testing.py
src/collective/twitter/portlets/twprofile.pt
src/collective/twitter/portlets/twprofile.py
src/collective/twitter/portlets/twsearch.pt
src/collective/twitter/portlets/twsearch.py
src/collective/twitter/portlets/Extensions/Install.py
src/collective/twitter/portlets/Extensions/__init__.py
src/collective/twitter/portlets/locales/collective.twitter.portlets.pot
src/collective/twitter/portlets/locales/es/LC_MESSAGES/collective.twitter.portlets.po
src/collective/twitter/portlets/profiles/default/browserlayer.xml
src/collective/twitter/portlets/profiles/default/collective.twitter.portlets_various.txt
src/collective/twitter/portlets/profiles/default/cssregistry.xml
src/collective/twitter/portlets/profiles/default/metadata.xml
src/collective/twitter/portlets/profiles/default/portlets.xml
src/collective/twitter/portlets/profiles/initial/cssregistry.xml
src/collective/twitter/portlets/profiles/initial/metadata.xml
src/collective/twitter/portlets/profiles/uninstall/portlets.xml
src/collective/twitter/portlets/static/style.css
src/collective/twitter/portlets/tests/__init__.py
src/collective/twitter/portlets/tests/base.py
src/collective/twitter/portlets/tests/test_profile_portlet.py
src/collective/twitter/portlets/tests/test_search_portlet.py
src/collective/twitter/portlets/tests/test_setup.py