Metadata-Version: 1.1
Name: collective.twitter.portlets
Version: 1.0b5
Summary: This product allows you to add different kinds of portlets to your site to get tweets.
Home-page: https://github.com/collective/collective.twitter.portlets
Author: Franco Pellegrini
Author-email: frapell@gmail.com
License: GPL
Keywords: plone twitter portlet
Platform: UNKNOWN
Classifier: Development Status :: 4 - Beta
Classifier: Environment :: Web Environment
Classifier: Framework :: Plone
Classifier: Framework :: Plone :: 4.1
Classifier: Framework :: Plone :: 4.2
Classifier: Framework :: Plone :: 4.3
Classifier: Intended Audience :: System Administrators
Classifier: License :: OSI Approved :: GNU General Public License (GPL)
Classifier: Operating System :: OS Independent
Classifier: Programming Language :: JavaScript
Classifier: Programming Language :: Python
Classifier: Programming Language :: Python :: 2.6
Classifier: Programming Language :: Python :: 2.7
Classifier: Topic :: Software Development :: Libraries :: Python Modules
